mathkit/__init__.py
mathkit/main.py
mathkit-4.2.3.dist-info/METADATA
mathkit-4.2.3.dist-info/WHEEL
mathkit-4.2.3.dist-info/top_level.txt
mathkit-4.2.3.dist-info/RECORD
