Metadata-Version: 2.1
Name: mathkit
Version: 4.2.3
Summary: Python library for mathematical functions
Home-page: https://github.com/theunkownhacker/mathkit
Author: TheUnkownHacker
Author-email: theunkownhacker@gmail.com
Classifier: Programming Language :: Python :: 3
Classifier: License :: OSI Approved :: MIT License
Classifier: Operating System :: OS Independent
Requires-Python: >=3.6
